pygame_chess_api/__init__.py
pygame_chess_api/api.py
pygame_chess_api/render.py
pygame_chess_api/assets/black_bishop.png
pygame_chess_api/assets/black_check.png
pygame_chess_api/assets/black_knight.png
pygame_chess_api/assets/black_pawn.png
pygame_chess_api/assets/black_queen.png
pygame_chess_api/assets/black_rook.png
pygame_chess_api/assets/black_square.png
pygame_chess_api/assets/square_of_highlight.png
pygame_chess_api/assets/square_of_in_check.png
pygame_chess_api/assets/square_of_kill.png
pygame_chess_api/assets/square_of_special.png
pygame_chess_api/assets/white_bishop.png
pygame_chess_api/assets/white_check.png
pygame_chess_api/assets/white_knight.png
pygame_chess_api/assets/white_pawn.png
pygame_chess_api/assets/white_queen.png
pygame_chess_api/assets/white_rook.png
pygame_chess_api/assets/white_square.png
pygame_chess_api-0.2.7.dist-info/LICENSE
pygame_chess_api-0.2.7.dist-info/METADATA
pygame_chess_api-0.2.7.dist-info/WHEEL
pygame_chess_api-0.2.7.dist-info/top_level.txt
pygame_chess_api-0.2.7.dist-info/RECORD
