Metadata-Version: 2.1
Name: pygame-chess-api
Version: 0.2.7
Summary: A chess API in python, provided with a fancy Pygame GUI
Author-email: LupyXev <lupyxev@protonmail.com>
License: MIT License
Project-URL: Documentation, https://pygame-chess-api.readthedocs.io/
Project-URL: Homepage, https://github.com/LupyXev/pygame_chess_api
Keywords: chess-engine,chess,pygame,chessboard,chess-game
Classifier: Programming Language :: Python :: 3
Classifier: License :: OSI Approved :: MIT License
Classifier: Operating System :: OS Independent
Requires-Python: >=3.6
License-File: LICENSE
